sprout/SPROUTObject.py
sprout/UncertaintyCalculator.py
sprout/__init__.py
sprout/classifiers/AutoEncoder.py
sprout/classifiers/Classifier.py
sprout/classifiers/__init__.py
sprout/utils/__init__.py
sprout/utils/dataset_utils.py
sprout/utils/general_utils.py
sprout/utils/sprout_utils.py
sprout_ml-0.90.dist-info/licenses/LICENSE
sprout_ml-0.90.dist-info/METADATA
sprout_ml-0.90.dist-info/WHEEL
sprout_ml-0.90.dist-info/top_level.txt
sprout_ml-0.90.dist-info/RECORD
