Metadata-Version: 2.4
Name: sprout-ml
Version: 0.90
Summary: SPROUT - a Safety wraPper thROugh ensembles of UncertainTy measures
Home-page: https://github.com/tommyippoz/SPROUT
Author: Tommaso Zoppi
Author-email: tommaso.zoppi@unifi.it
Keywords: machine learning,safety wrapper,safety monitor,uncertainty measures,ensemble
Classifier: Programming Language :: Python :: 3
Classifier: License :: OSI Approved :: MIT License
Classifier: Operating System :: OS Independent
License-File: LICENSE
Dynamic: author
Dynamic: author-email
Dynamic: classifier
Dynamic: description
Dynamic: description-content-type
Dynamic: home-page
Dynamic: keywords
Dynamic: license-file
Dynamic: summary
